_pxdgen.py
pxdgen/__init__.py
pxdgen/constants.py
pxdgen/cursors.py
pxdgen/extensions.py
pxdgen/utils/__init__.py
pxdgen/utils/tab_writer.py
pxdgen/utils/utils.py
pxdgen-1.1.0.dist-info/COPYING
pxdgen-1.1.0.dist-info/METADATA
pxdgen-1.1.0.dist-info/WHEEL
pxdgen-1.1.0.dist-info/entry_points.txt
pxdgen-1.1.0.dist-info/top_level.txt
pxdgen-1.1.0.dist-info/RECORD
