Metadata-Version: 2.1
Name: pxdgen
Version: 1.1.0
Summary: A tool for converting one or more C/C++ headers to Cython pxd files.
Home-page: https://github.com/earowley/pxdgen
Author: Eric Rowley
Author-email: earowley23@gmail.com
License: GNU GPLv3
Requires-Python: ~=3.6
License-File: COPYING
Requires-Dist: clang
Requires-Dist: colorama
